{
    "best_model_name": "GradientBoosting",
    "cv_results": [
        {
            "model_name": "LinearRegression",
            "cv_r2_mean": 0.15657149359411587,
            "cv_r2_std": 0.01901225344292436
        },
        {
            "model_name": "Ridge",
            "cv_r2_mean": 0.15658501550553577,
            "cv_r2_std": 0.019025133669845082
        },
        {
            "model_name": "Lasso",
            "cv_r2_mean": 0.1488552045371545,
            "cv_r2_std": 0.02053480897767001
        },
        {
            "model_name": "DecisionTree",
            "cv_r2_mean": 0.2153336144211151,
            "cv_r2_std": 0.02758558475707632
        },
        {
            "model_name": "RandomForest",
            "cv_r2_mean": 0.37303259781440723,
            "cv_r2_std": 0.01741584440777021
        },
        {
            "model_name": "GradientBoosting",
            "cv_r2_mean": 0.38324737716069157,
            "cv_r2_std": 0.012620768799713038
        }
    ],
    "test_rmse": 1.0388321192947778
}